threshopt/__init__.py
threshopt/core.py
threshopt/cv/__init__.py
threshopt/cv/cv.py
threshopt/metrics/__init__.py
threshopt/metrics/metrics.py
threshopt/plotting/__init__.py
threshopt/plotting/plot_auc.py
threshopt/plotting/plot_confusion.py
threshopt/thresholds/__init__.py
threshopt/thresholds/binary_threshold.py
threshopt/thresholds/multiclass_threshold.py
threshopt/utils/__init__.py
threshopt/utils/utils.py
threshopt-1.1.0.dist-info/LICENSE
threshopt-1.1.0.dist-info/METADATA
threshopt-1.1.0.dist-info/WHEEL
threshopt-1.1.0.dist-info/top_level.txt
threshopt-1.1.0.dist-info/RECORD
