Metadata-Version: 2.2
Name: threshopt
Version: 1.1.0
Summary: Automatic threshold optimization for classifiers.
Home-page: https://github.com/salvo-zizzi/threshopt
Author: Salvatore Zizzi
Author-email: Salvatore Zizzi <salvo.zizzi@gmail.com>
License: Apache-2.0
Project-URL: Homepage, https://github.com/salvo-zizzi/threshopt
Requires-Python: >=3.7
License-File: LICENSE
Requires-Dist: scikit-learn
Requires-Dist: matplotlib
Requires-Dist: numpy
Dynamic: author
Dynamic: home-page
Dynamic: requires-python
